{
    "542863411": "Oil of Lesser Alchemy",
    "543321954": "Bob Ross",
    "543977570": "Large Blue Potion",
    "544436322": "Small Blue Potion",
    "543584360": "Full Healing Potion",
    "544174184": "Healing Potion",
    "543584365": "Full Mana Potion",
    "544174189": "Mana Potion",
    "543977586": "Large Red Potion",
    "544436338": "Small Red Potion",
    "960067940": "Mystic Dye 99",
    "825258596": "Depleted Riftstone (1)",
    "842035812": "Depleted Riftstone (2)",
    "858813028": "Depleted Riftstone (3)",
    "875590244": "Depleted Riftstone (4)",
    "892367460": "Depleted Riftstone (5)",
    "909144676": "Depleted Riftstone (1)",
    "925921892": "Depleted Riftstone (2)",
    "942699108": "Depleted Riftstone (3)",
    "959476324": "Depleted Riftstone (4)",
    "808546916": "Depleted Riftstone (5)",
    "825324132": "Depleted Riftstone (6)",
    "842101348": "Depleted Riftstone (7)",
    "858878564": "Depleted Riftstone (8)",
    "875655780": "Depleted Riftstone (9)",
    "892432996": "Depleted Riftstone (10)",
    "825258601": "Charged Riftstone (1)",
    "842035817": "Charged Riftstone (2)",
    "858813033": "Charged Riftstone (3)",
    "875590249": "Charged Riftstone (4)",
    "892367465": "Charged Riftstone (5)",
    "909144681": "Charged Riftstone (1)",
    "925921897": "Charged Riftstone (2)",
    "942699113": "Charged Riftstone (3)",
    "959476329": "Charged Riftstone (4)",
    "808546921": "Charged Riftstone (5)",
    "825324137": "Charged Riftstone (6)",
    "842101353": "Charged Riftstone (7)",
    "858878569": "Charged Riftstone (8)",
    "875655785": "Charged Riftstone (9)",
    "892433001": "Charged Riftstone (10)",
    "2019652715": "Pulsating Worldstone Shard",
    "2019718251": "Pulsating Worldstone Shard",
    "2019783787": "Pulsating Worldstone Shard",
    "2019849323": "Pulsating Worldstone Shard",
    "2019914859": "Pulsating Worldstone Shard",
    "1801807212": ":leek:",
    "544894316": "Season 36: Pandemonium Event Award",
    "543321959": "The Goblin King Event Award",
    "544435564": "The Last Man Standing Event Award",
    "543375459": "Moon Symbol",
    "540629027": "Griswold's Treasure",
    "540292466": "Krys Rune",
    "540358002": "Auhe Rune",
    "540423538": "Sha'ad Rune",
    "544891493": "Amulet",
    "544436345": "Antidote Potion",
    "544435575": "Thawing Potion",
    "544436342": "Stamina Potion",
    "544895586": "Brain",
    "544897381": "Eye",
    "543648870": "Flag",
    "543649382": "Fang",
    "544109160": "Horn",
    "544502376": "Heart",
    "544694634": "Jawbone",
    "543976561": "Quill",
    "544891763": "Scalp",
    "543977331": "Soul",
    "543518835": "Spleen",
    "543973748": "Tail",
    "828599411": "Scroll of Athulua",
    "1480879990": "Enchanting Crystal",
    "539701569": "Creepy Shrine (9)",
    "539701825": "Creepy Shrine (8)",
    "539702081": "Creepy Shrine (7)",
    "539702337": "Creepy Shrine (6)",
    "539702593": "Creepy Shrine (5)",
    "539702849": "Creepy Shrine (4)",
    "539703105": "Creepy Shrine (3)",
    "539703361": "Creepy Shrine (2)",
    "539703617": "Creepy Shrine (1)",
    "539701570": "Abandoned Shrine (9)",
    "539701826": "Abandoned Shrine (8)",
    "539702082": "Abandoned Shrine (7)",
    "539702338": "Abandoned Shrine (6)",
    "539702594": "Abandoned Shrine (5)",
    "539702850": "Abandoned Shrine (4)",
    "539703106": "Abandoned Shrine (3)",
    "539703362": "Abandoned Shrine (2)",
    "539703618": "Abandoned Shrine (1)",
    "539701571": "Quiet Shrine (9)",
    "539701827": "Quiet Shrine (8)",
    "539702083": "Quiet Shrine (7)",
    "539702339": "Quiet Shrine (6)",
    "539702595": "Quiet Shrine (5)",
    "539702851": "Quiet Shrine (4)",
    "539703107": "Quiet Shrine (3)",
    "539703363": "Quiet Shrine (2)",
    "539703619": "Quiet Shrine (1)",
    "539701572": "Eerie Shrine (9)",
    "539701828": "Eerie Shrine (8)",
    "539702084": "Eerie Shrine (7)",
    "539702340": "Eerie Shrine (6)",
    "539702596": "Eerie Shrine (5)",
    "539702852": "Eerie Shrine (4)",
    "539703108": "Eerie Shrine (3)",
    "539703364": "Eerie Shrine (2)",
    "539703620": "Eerie Shrine (1)",
    "539701573": "Weird Shrine (9)",
    "539701829": "Weird Shrine (8)",
    "539702085": "Weird Shrine (7)",
    "539702341": "Weird Shrine (6)",
    "539702597": "Weird Shrine (5)",
    "539702853": "Weird Shrine (4)",
    "539703109": "Weird Shrine (3)",
    "539703365": "Weird Shrine (2)",
    "539703621": "Weird Shrine (1)",
    "539701574": "Intimidating Shrine (9)",
    "539701830": "Intimidating Shrine (8)",
    "539702086": "Intimidating Shrine (7)",
    "539702342": "Intimidating Shrine (6)",
    "539702598": "Intimidating Shrine (5)",
    "539702854": "Intimidating Shrine (4)",
    "539703110": "Intimidating Shrine (3)",
    "539703366": "Intimidating Shrine (2)",
    "539703622": "Intimidating Shrine (1)",
    "539701575": "Tainted Shrine (9)",
    "539701831": "Tainted Shrine (8)",
    "539702087": "Tainted Shrine (7)",
    "539702343": "Tainted Shrine (6)",
    "539702599": "Tainted Shrine (5)",
    "539702855": "Tainted Shrine (4)",
    "539703111": "Tainted Shrine (3)",
    "539703367": "Tainted Shrine (2)",
    "539703623": "Tainted Shrine (1)",
    "539701576": "Fascinating Shrine (9)",
    "539701832": "Fascinating Shrine (8)",
    "539702088": "Fascinating Shrine (7)",
    "539702344": "Fascinating Shrine (6)",
    "539702600": "Fascinating Shrine (5)",
    "539702856": "Fascinating Shrine (4)",
    "539703112": "Fascinating Shrine (3)",
    "539703368": "Fascinating Shrine (2)",
    "539703624": "Fascinating Shrine (1)",
    "539701577": "Ornate Shrine (9)",
    "539701833": "Ornate Shrine (8)",
    "539702089": "Ornate Shrine (7)",
    "539702345": "Ornate Shrine (6)",
    "539702601": "Ornate Shrine (5)",
    "539702857": "Ornate Shrine (4)",
    "539703113": "Ornate Shrine (3)",
    "539703369": "Ornate Shrine (2)",
    "539703625": "Ornate Shrine (1)",
    "539701578": "Sacred Shrine (9)",
    "539701834": "Sacred Shrine (8)",
    "539702090": "Sacred Shrine (7)",
    "539702346": "Sacred Shrine (6)",
    "539702602": "Sacred Shrine (5)",
    "539702858": "Sacred Shrine (4)",
    "539703114": "Sacred Shrine (3)",
    "539703370": "Sacred Shrine (2)",
    "539703626": "Sacred Shrine (1)",
    "539701579": "Shimmering Shrine (9)",
    "539701835": "Shimmering Shrine (8)",
    "539702091": "Shimmering Shrine (7)",
    "539702347": "Shimmering Shrine (6)",
    "539702603": "Shimmering Shrine (5)",
    "539702859": "Shimmering Shrine (4)",
    "539703115": "Shimmering Shrine (3)",
    "539703371": "Shimmering Shrine (2)",
    "539703627": "Shimmering Shrine (1)",
    "539701581": "Spiritual Shrine (9)",
    "539701837": "Spiritual Shrine (8)",
    "539702093": "Spiritual Shrine (7)",
    "539702349": "Spiritual Shrine (6)",
    "539702605": "Spiritual Shrine (5)",
    "539702861": "Spiritual Shrine (4)",
    "539703117": "Spiritual Shrine (3)",
    "539703373": "Spiritual Shrine (2)",
    "539703629": "Spiritual Shrine (1)",
    "539701582": "Magical Shrine (9)",
    "539701838": "Magical Shrine (8)",
    "539702094": "Magical Shrine (7)",
    "539702350": "Magical Shrine (6)",
    "539702606": "Magical Shrine (5)",
    "539702862": "Magical Shrine (4)",
    "539703118": "Magical Shrine (3)",
    "539703374": "Magical Shrine (2)",
    "539703630": "Magical Shrine (1)",
    "539701583": "Enchanted Shrine (9)",
    "539701839": "Enchanted Shrine (8)",
    "539702095": "Enchanted Shrine (7)",
    "539702351": "Enchanted Shrine (6)",
    "539702607": "Enchanted Shrine (5)",
    "539702863": "Enchanted Shrine (4)",
    "539703119": "Enchanted Shrine (3)",
    "539703375": "Enchanted Shrine (2)",
    "539703631": "Enchanted Shrine (1)",
    "539701585": "Hidden Shrine (9)",
    "539701841": "Hidden Shrine (8)",
    "539702097": "Hidden Shrine (7)",
    "539702353": "Hidden Shrine (6)",
    "539702609": "Hidden Shrine (5)",
    "539702865": "Hidden Shrine (4)",
    "539703121": "Hidden Shrine (3)",
    "539703377": "Hidden Shrine (2)",
    "539703633": "Hidden Shrine (1)",
    "539701586": "Trinity Shrine (9)",
    "539701842": "Trinity Shrine (8)",
    "539702098": "Trinity Shrine (7)",
    "539702354": "Trinity Shrine (6)",
    "539702610": "Trinity Shrine (5)",
    "539702866": "Trinity Shrine (4)",
    "539703122": "Trinity Shrine (3)",
    "539703378": "Trinity Shrine (2)",
    "539703634": "Trinity Shrine (1)",
    "540110179": "Cycle",
    "540175715": "Cycle",
    "540241251": "Cycle",
    "540030066": "unused",
    "540030322": "unused",
    "540043056": "unused",
    "540095602": "unused",
    "540098593": "unused",
    "540108592": "unused",
    "540111973": "unused",
    "540161138": "unused",
    "540164129": "unused",
    "540174128": "unused",
    "540178789": "unused",
    "540226674": "unused",
    "540229665": "unused",
    "540244325": "unused",
    "540291954": "unused",
    "540292210": "unused",
    "540295201": "unused",
    "540309861": "unused",
    "540357490": "unused",
    "540357746": "unused",
    "540360737": "unused",
    "540375090": "unused",
    "540423026": "unused",
    "540423282": "unused",
    "540440626": "unused",
    "540488562": "unused",
    "540488818": "unused",
    "540489313": "unused",
    "540501808": "unused",
    "540506162": "unused",
    "540554098": "unused",
    "540554354": "unused",
    "540567344": "unused",
    "540571698": "unused",
    "540619634": "unused",
    "540619890": "unused",
    "540637234": "unused",
    "540637541": "unused",
    "828600930": "unused",
    "828992883": "unused",
    "845378146": "unused",
    "845770099": "unused",
    "862155362": "unused",
    "878932578": "unused",
    "895709794": "unused",
    "912487010": "unused",
    "1852728691": "unused"
}